Metadata-Version: 2.1
Name: example-pkg-your-lifefornazgul
Version: 0.2.1
Summary: Just a tutorial
Home-page: https://github.com/pypa/sampleproject
Author: Maxim Galkin
Author-email: m.galkin@outlook.com
License: UNKNOWN
Platform: UNKNOWN
Classifier: Programming Language :: Python :: 3
Classifier: License :: OSI Approved :: MIT License
Classifier: Operating System :: OS Independent
